{
  "products": [
    {
      "id": "R63A5",
      "name": "Blue Handbag",
      "info": "Leather bag",
      "description": "Stylish blue leather bag",
      "details": "The blue handbag is made of high-quality leather, providing durability and a luxurious feel. It features a spacious main compartment with multiple pockets for convenient organization. The adjustable shoulder strap allows for comfortable carrying. Whether for a casual outing or a formal event, this blue handbag is a perfect accessory to complement your style.",
      "brand": "Zara",
      "size": "Medium",
      "category": "handbags",
      "color": "Blue",
      "price": 59.99,
      "discount": 0.40,
      "qty": 8,
      "url": "https://www.prada.com/content/dam/pradanux/e-commerce/2023/05/galleria/snodo_essentials/ww/mosaic_2/Card_1_DT.jpg",
      "rating": {
        "oneStars": 2,
        "twoStars": 1,
        "threeStars": 3,
        "fourStars": 5,
        "fiveStars": 4,
        "averageStars": 3.6,
        "totalRatings": 15
      },
      "reviews": 63,
      "releaseDate": "2022-04-15",
      "popularity": 8
    },
    {
      "id": "DHU72",
      "name": "Satchel",
      "info": "Chic satchel",
      "description": "Chic maroon red faux leather satchel",
      "details": "The maroon red satchel is crafted from high-quality faux leather, providing a cruelty-free alternative with a sophisticated look. It features a spacious main compartment, multiple interior pockets, and a secure zip closure. The adjustable shoulder strap offers versatility in styling. With its elegant design and practicality, this maroon red satchel is a must-have accessory for any fashion-forward individual.",
      "brand": "Zara",
      "size": "Medium",
      "category": "handbags",
      "color": "Maroon Red",
      "price": 49.99,
      "discount": 0.20,
      "qty": 5,
      "url": "https://www.prada.com/content/dam/pradanux/e-commerce/2023/05/galleria/snodo_essentials/ww/banner_cleo_v2/banner_DT.jpg",
      "rating": {
        "oneStars": 1,
        "twoStars": 3,
        "threeStars": 2,
        "fourStars": 4,
        "fiveStars": 3,
        "averageStars": 3.1,
        "totalRatings": 13
      },
      "reviews": 42,
      "releaseDate": "2022-08-02",
      "popularity": 7
    },
    {
      "id": "P89Q2",
      "name": "Red Tote",
      "info": "Elegant tote",
      "description": "Elegant crimson red leather tote",
      "details": "The crimson red tote exudes elegance and sophistication. Made from premium leather, it offers a spacious interior with multiple compartments to keep your essentials organized. The sturdy handles and detachable shoulder strap provide versatility in carrying options. Whether for work or a special occasion, this crimson red tote is a statement piece that adds a touch of luxury to your ensemble.",
      "brand": "Dolce & Gabbana",
      "size": "Big",
      "category": "handbags",
      "color": "Crimson Red",
      "price": 179.99,
      "discount": 0.10,
      "qty": 12,
      "url": "https://static.zara.net/photos///2023/S/1/1/p/6899/010/850/2/w/535/6899010850_15_1_1.jpg?ts=1688122625170",
      "rating": {
        "oneStars": 0,
        "twoStars": 2,
        "threeStars": 3,
        "fourStars": 5,
        "fiveStars": 4,
        "averageStars": 3.9,
        "totalRatings": 14
      },
      "reviews": 112,
      "releaseDate": "2021-12-05",
      "popularity": 9
    },
    {
      "id": "G36T9",
      "name": "Seinna Crossbody",
      "info": "Compact",
      "description": "Compact seinna pink faux leather crossbody",
      "details": "The seinna pink crossbody is a compact and versatile accessory, perfect for carrying your essentials on the go. Made from high-quality faux leather, it combines durability with a soft touch. The adjustable strap allows for comfortable wearing, and the multiple pockets provide convenient organization. With its stylish design and practicality, this seinna pink crossbody is an ideal companion for everyday adventures.",
      "brand": "Dolce & Gabbana",
      "size": "Small",
      "category": "handbags",
      "color": "Seinna Pink",
      "price": 69.99,
      "discount": 0.30,
      "qty": 10,
      "url": "https://www.dolcegabbana.com/dw/image/v2/AAGA_PRD/on/demandware.static/-/Sites-15/default/dw386fb1fd/images/zoom/BB7287A1471_80315_0.jpg?sw=640&sh=816&sm=fit",
      "rating": {
        "oneStars": 1,
        "twoStars": 2,
        "threeStars": 4,
        "fourStars": 3,
        "fiveStars": 5,
        "averageStars": 3.9,
        "totalRatings": 15
      },
      "reviews": 87,
      "releaseDate": "2022-02-19",
      "popularity": 8
    },
    {
      "id": "H24F7",
      "name": "Backpack",
      "info": "Sturdy backpack",
      "description": "Sturdy teal nylon backpack",
      "details": "The teal backpack is designed for both style and functionality. Made from durable nylon, it offers ample storage space with multiple compartments and pockets, including a padded laptop sleeve. The adjustable shoulder straps and padded back ensure comfortable carrying, making it an ideal choice for students or travelers. Whether for daily commutes or weekend getaways, this teal backpack is a reliable companion.",
      "brand": "Hennes & Mauritz",
      "size": "Big",
      "category": "handbags",
      "color": "Teal",
      
      "price": 79.99,
      "discount": 0.50,
      "qty": 3,
      "url": "https://www.dolcegabbana.com/dw/image/v2/AAGA_PRD/on/demandware.static/-/Sites-15/default/dw16001949/images/zoom/BB6002AI413_80999_0.jpg?sw=640&sh=816&sm=fit",
      "rating": {
        "oneStars": 0,
        "twoStars": 1,
        "threeStars": 2,
        "fourStars": 3,
        "fiveStars": 5,
        "averageStars": 4.1,
        "totalRatings": 11
      },
      "reviews": 34,
      "releaseDate": "2022-06-27",
      "popularity": 6
    },
    {
      "id": "B63D4",
      "name": "Clutch",
      "info": "Elegant clutch",
      "description": "Elegant aquamarine satin clutch",
      "details": "The aquamarine clutch is an elegant accessory that adds a touch of glamour to any ensemble. Crafted from luxurious satin, it features a compact design with a secure snap closure. The interior is lined with soft fabric and offers enough space for your essentials. Whether for a wedding, cocktail party, or a special occasion, this aquamarine clutch is the perfect companion to elevate your style.",
      "brand": "Hennes & Mauritz",
      "size": "Small",
      "category": "handbags",
      "color": "aquamarine",
      "price": 39.99,
      "discount": 0.60,
      "qty": 6,
      "url": "https://www.dolcegabbana.com/dw/image/v2/AAGA_PRD/on/demandware.static/-/Sites-15/default/dw42e1ad33/images/zoom/BB6002AM102_HY13M_0.jpg?sw=640&sh=816&sm=fit",
      "rating": {
        "oneStars": 0,
        "twoStars": 0,
        "threeStars": 2,
        "fourStars": 3,
        "fiveStars": 4,
        "averageStars": 4.0,
        "totalRatings": 9
      },
      "reviews": 17,
      "releaseDate": "2022-11-11",
      "popularity": 5
    },
    {
      "id": "C28V6",
      "name": "Hobo Bag",
      "info": "Chic bag",
      "description": "Chic off white leather hobo bag",
      "details": "The off white hobo bag combines style and functionality in a single accessory. Made from premium leather, it offers a roomy interior with a magnetic closure for easy access to your belongings. The adjustable shoulder strap provides comfort, and the additional zippered pocket keeps your essentials secure. With its versatile design and timeless appeal, this off white hobo bag is a fashionable choice for everyday use.",
      "brand": "Chanel",
      "size": "Big",
      "category": "handbags",
      "color": "off white",
      "price": 249.99,
      "discount": 0.15,
      "qty": 9,
      "url": "https://www.dolcegabbana.com/dw/image/v2/AAGA_PRD/on/demandware.static/-/Sites-15/default/dw887df5c4/images/zoom/BB7347AW437_87124_0.jpg?sw=640&sh=816&sm=fit",
      "rating": {
        "oneStars": 1,
        "twoStars": 1,
        "threeStars": 2,
        "fourStars": 5,
        "fiveStars": 4,
        "averageStars": 3.8,
        "totalRatings": 13
      },
      "reviews": 56,
      "releaseDate": "2021-09-09",
      "popularity": 7
    },
    {
      "id": "P59M3",
      "name": "Satchel",
      "info": "Vibrant satchel",
      "description": "Vibrant muave orange faux leather satchel",
      "details": "The muave orange satchel is a vibrant and eye-catching accessory. Crafted from high-quality faux leather, it offers durability and a luxurious look. The spacious main compartment and multiple pockets provide ample storage for your belongings. The detachable shoulder strap allows for versatile styling options. With its bold color and practical design, this muave orange satchel is sure to make a statement wherever you go.",
      "brand": "Chanel",
      "size": "Medium",
      "category": "handbags",
      "color": "muave orange",
      "price": 149.99,
      "discount": 0.25,
      "qty": 7,
      "url": "https://www.dolcegabbana.com/dw/image/v2/AAGA_PRD/on/demandware.static/-/Sites-15/default/dwe77c1f0b/images/zoom/BB6711AV893_80002_0.jpg?sw=640&sh=816&sm=fit",
      "rating": {
        "oneStars": 0,
        "twoStars": 2,
        "threeStars": 3,
        "fourStars": 4,
        "fiveStars": 5,
        "averageStars": 4.1,
        "totalRatings": 14
      },
      "reviews": 92,
      "releaseDate": "2022-01-22",
      "popularity": 8
    },
    {
      "id": "Z73R1",
      "name": "Blue Tote",
      "info": "Classic tote",
      "description": "Classic blue leather tote",
      "details": "The blue leather tote is a timeless accessory that combines style and practicality. Made from genuine leather, it offers a spacious interior with a zippered pocket and multiple compartments for organization. The sturdy handles and detachable shoulder strap provide versatility in carrying options. With its classic design and durable construction, this blue leather tote is a perfect companion for everyday activities and work.",
      "brand": "Prada",
      "size": "Big",
      "category": "handbags",
      "color": "Blue",
      "price": 289.99,
      "discount": 0.20,
      "qty": 11,
      "url": "https://www.dolcegabbana.com/dw/image/v2/AAGA_PRD/on/demandware.static/-/Sites-15/default/dw1ee6cca9/images/zoom/BI1416AW121_89869_0.jpg?sw=640&sh=816&sm=fit",
      "rating": {
        "oneStars": 0,
        "twoStars": 0,
        "threeStars": 1,
        "fourStars": 4,
        "fiveStars": 5,
        "averageStars": 4.5,
        "totalRatings": 10
      },
      "reviews": 31,
      "releaseDate": "2021-07-27",
      "popularity": 8
    },
    {
      "id": "D58N7",
      "name": "Shoulder Bag",
      "info": "Elegant bag",
      "description": "Elegant maroon red leather shoulder bag",
      "details": "The maroon red shoulder bag is an elegant accessory that complements any outfit. Crafted from high-quality leather, it showcases a sleek design with a spacious main compartment and additional pockets for organization. The adjustable shoulder strap ensures a comfortable fit. Whether for a day at the office or a night out, this maroon red shoulder bag combines style and functionality for a sophisticated look.",
      "brand": "Prada",
      "size": "Medium",
      "category": "handbags",
      "color": "Maroon Red",
      "price": 229.99,
      "discount": 0.30,
      "qty": 6,
      "url": "https://www.dolcegabbana.com/dw/image/v2/AAGA_PRD/on/demandware.static/-/Sites-15/default/dw4e2200f0/images/zoom/BB5970A8N11_8B767_0.jpg?sw=640&sh=816&sm=fit",
      "rating": {
        "oneStars": 1,
        "twoStars": 2,
        "threeStars": 3,
        "fourStars": 3,
        "fiveStars": 4,
        "averageStars": 3.4,
        "totalRatings": 13
      },
      "reviews": 39,
      "releaseDate": "2022-03-09",
      "popularity": 7
    },
    {
      "id": "B39J4",
      "name": "Seinna",
      "info": "Compact crossbody",
      "description": "Compact seinna pink faux leather crossbody",
      "details": "The seinna pink crossbody is a compact and versatile accessory, perfect for carrying your essentials on the go. Made from high-quality faux leather, it combines durability with a soft touch. The adjustable strap allows for comfortable wearing, and the multiple pockets provide convenient organization. With its stylish design and practicality, this seinna pink crossbody is an ideal companion for everyday adventures.",
      "brand": "Biba",
      "size": "Small",
      "category": "handbags",
      "color": "Seinna Pink",
      "price": 89.99,
      "discount": 0.10,
      "qty": 8,
      "url": "https://static.zara.net/photos///2023/W/1/1/p/6527/010/040/2/w/535/6527010040_15_6_1.jpg?ts=1677773560769",
      "rating": {
        "oneStars": 0,
        "twoStars": 1,
        "threeStars": 4,
        "fourStars": 3,
        "fiveStars": 5,
        "averageStars": 4.0,
        "totalRatings": 13
      },
      "reviews": 63,
      "releaseDate": "2022-08-15",
      "popularity": 6
    },
    {
      "id": "Z79X6",
      "name": "Teal Backpack",
      "info": "Sturdy backpack",
      "description": "Sturdy teal nylon backpack",
      "details": "The teal backpack is designed for both style and functionality. Made from durable nylon, it offers ample storage space with multiple compartments and pockets, including a padded laptop sleeve. The adjustable shoulder straps and padded back ensure comfortable carrying, making it an ideal choice for students or travelers. Whether for daily commutes or weekend getaways, this teal backpack is a reliable companion.",
      "brand": "Biba",
      "size": "Big",
      "category": "handbags",
      "color": "Teal",
      "price": 99.99,
      "discount": 0.25,
      "qty": 4,
      "url": "https://static.zara.net/photos///2023/S/1/1/p/6109/010/808/2/w/535/6109010808_15_2_1.jpg?ts=1688398229271",
      "rating": {
        "oneStars": 0,
        "twoStars": 0,
        "threeStars": 3,
        "fourStars": 4,
        "fiveStars": 5,
        "averageStars": 4.3,
        "totalRatings": 12
      },
      "reviews": 47,
      "releaseDate": "2022-10-01",
      "popularity": 7
    },
    {
      "id": "D43K8",
      "name": "Clutch",
      "info": "Elegant clutch",
      "description": "Elegant aquamarine satin clutch",
      "details": "The aquamarine clutch is an elegant accessory that adds a touch of glamour to any ensemble. Crafted from luxurious satin, it features a compact design with a secure snap closure. The interior is lined with soft fabric and offers enough space for your essentials. Whether for a wedding, cocktail party, or a special occasion, this aquamarine clutch is the perfect companion to elevate your style.",
      "brand": "Zara",
      "size": "Small",
      "category": "handbags",
      "color": "aquamarine",
      "price": 49.99,
      "discount": 0.50,
      "qty": 12,
      "url": "https://www.prada.com/content/dam/pradabkg_products/1/1BA/1BA896/NZVF0E18/1BA896_NZV_F0E18_V_EOO_SLF.jpg/_jcr_content/renditions/cq5dam.web.hebebed.800.800.jpg",
      "rating": {
        "oneStars": 0,
        "twoStars": 1,
        "threeStars": 2,
        "fourStars": 3,
        "fiveStars": 5,
        "averageStars": 3.9,
        "totalRatings": 11
      },
      "reviews": 28,
      "releaseDate": "2021-12-31",
      "popularity": 6
    },
    {
      "id": "H89R2",
      "name": "Off Bag",
      "info": "Chic bag",
      "description": "Chic off white leather hobo bag",
      "details": "The off white hobo bag combines style and functionality in a single accessory. Made from premium leather, it offers a roomy interior with a magnetic closure for easy access to your belongings. The adjustable shoulder strap provides comfort, and the additional zippered pocket keeps your essentials secure. With its versatile design and timeless appeal, this off white hobo bag is a fashionable choice for everyday use.",
      "brand": "Zara",
      "size": "Big",
      "category": "handbags",
      "color": "off white",
      "price": 159.99,
      "discount": 0.20,
      "qty": 9,
      "url": "https://www.prada.com/content/dam/pradabkg_products/1/1BA/1BA906/NZVF0458/1BA906_NZV_F0458_V_OOM_SLF.jpg/_jcr_content/renditions/cq5dam.web.hebebed.800.800.jpg",
      "rating": {
        "oneStars": 1,
        "twoStars": 2,
        "threeStars": 4,
        "fourStars": 4,
        "fiveStars": 5,
        "averageStars": 4.2,
        "totalRatings": 16
      },
      "reviews": 61,
      "releaseDate": "2022-06-25",
      "popularity": 8
    },
    {
      "id": "P76L5",
      "name": "Orange Satchel",
      "info": "Vibrant satchel",
      "description": "Vibrant muave orange faux leather satchel",
      "details": "The muave orange satchel is a vibrant and eye-catching accessory. Crafted from high-quality faux leather, it offers durability and a luxurious look. The spacious main compartment and multiple pockets provide ample storage for your belongings. The detachable shoulder strap allows for versatile styling options. With its bold color and practical design, this muave orange satchel is sure to make a statement wherever you go.",
      "brand": "Dolce & Gabbana",
      "size": "Medium",
      "category": "handbags",
      "color": "muave orange",
      "price": 199.99,
      "discount": 0.15,
      "qty": 5,
      "url": "https://www.prada.com/content/dam/pradabkg_products/1/1BA/1BA906/NZVF0049/1BA906_NZV_F0049_V_EOM_SLF.jpg/_jcr_content/renditions/cq5dam.web.hebebed.800.800.jpg",
      "rating": {
        "oneStars": 0,
        "twoStars": 1,
        "threeStars": 2,
        "fourStars": 3,
        "fiveStars": 4,
        "averageStars": 3.8,
        "totalRatings": 10
      },
      "reviews": 23,
      "releaseDate": "2022-02-14",
      "popularity": 6
    },
    {
      "id": "Z22F9",
      "name": "Leather",
      "info": "Classic tote",
      "description": "Classic blue leather tote",
      "details": "The blue leather tote is a timeless accessory that combines style and practicality. Made from genuine leather, it offers a spacious interior with a zippered pocket and multiple compartments for organization. The sturdy handles and detachable shoulder strap provide versatility in carrying options. With its classic design and durable construction, this blue leather tote is a perfect companion for everyday activities and work.",
      "brand": "Dolce & Gabbana",
      "size": "Big",
      "category": "handbags",
      "color": "Blue",
      "price": 289.99,
      "discount": 0.10,
      "qty": 10,
      "url": "https://www.prada.com/content/dam/pradabkg_products/1/1BA/1BA863/NZVF0002/1BA863_NZV_F0002_V_EOO_SLF.jpg/_jcr_content/renditions/cq5dam.web.hebebed.800.800.jpg",
      "rating": {
        "oneStars": 0,
        "twoStars": 1,
        "threeStars": 3,
        "fourStars": 5,
        "fiveStars": 5,
        "averageStars": 4.4,
        "totalRatings": 14
      },
      "reviews": 48,
      "releaseDate": "2021-11-10",
      "popularity": 8
    },
    {
      "id": "D17M8",
      "name": "Red Shoulder",
      "info": "Elegant bag",
      "description": "Elegant maroon red leather shoulder bag",
      "details": "The maroon red shoulder bag is an elegant accessory that complements any outfit. Crafted from high-quality leather, it showcases a sleek design with a spacious main compartment and additional pockets for organization. The adjustable shoulder strap ensures a comfortable fit. Whether for a day at the office or a night out, this maroon red shoulder bag combines style and functionality for a sophisticated look.",
      "brand": "Dolce & Gabbana",
      "size": "Medium",
      "category": "handbags",
      "color": "Maroon Red",
      "price": 229.99,
      "discount": 0.20,
      "qty": 7,
      "url": "https://www.prada.com/content/dam/pradabkg_products/1/1BA/1BA906/NZVF0002/1BA906_NZV_F0002_V_EOM_SLF.jpg/_jcr_content/renditions/cq5dam.web.hebebed.800.800.jpg",
      "rating": {
        "oneStars": 0,
        "twoStars": 1,
        "threeStars": 2,
        "fourStars": 3,
        "fiveStars": 4,
        "averageStars": 3.8,
        "totalRatings": 10
      },
      "reviews": 35,
      "releaseDate": "2022-04-02",
      "popularity": 7
    },
    {
      "id": "H54R3",
      "name": "Pink Crossbody",
      "info": "Compact crossbody",
      "description": "Compact seinna pink faux leather crossbody",
      "details": "The seinna pink crossbody is a compact and versatile accessory, perfect for carrying your essentials on the go. Made from high-quality faux leather, it combines durability with a soft touch. The adjustable strap allows for comfortable wearing, and the multiple pockets provide convenient organization. With its stylish design and practicality, this seinna pink crossbody is an ideal companion for everyday adventures.",
      "brand": "Chanel",
      "size": "Small",
      "category": "handbags",
      "color": "Seinna Pink",
      "price": 89.99,
      "discount": 0.25,
      "qty": 6,
      "url": "https://static.zara.net/photos///2023/W/1/1/p/6838/910/092/2/w/581/6838910092_15_3_1.jpg?ts=1683803601198",
      "rating": {
        "oneStars": 0,
        "twoStars": 0,
        "threeStars": 3,
        "fourStars": 4,
        "fiveStars": 5,
        "averageStars": 4.3,
        "totalRatings": 12
      },
      "reviews": 52,
      "releaseDate": "2022-07-18",
      "popularity": 6
    },
    {
      "id": "B26G4",
      "name": "Backpack",
      "info": "Sturdy backpack",
      "description": "Sturdy teal nylon backpack",
      "details": "The teal backpack is designed for both style and functionality. Made from durable nylon, it offers ample storage space with multiple compartments and pockets, including a padded laptop sleeve. The adjustable shoulder straps and padded back ensure comfortable carrying, making it an ideal choice for students or travelers. Whether for daily commutes or weekend getaways, this teal backpack is a reliable companion.",
      "brand": "Chanel",
      "size": "Big",
      "category": "handbags",
      "color": "Teal",
      "price": 99.99,
      "discount": 0.25,
      "qty": 4,
      "url": "https://static.zara.net/photos///2023/W/1/1/p/6393/010/716/2/w/634/6393010716_15_2_1.jpg?ts=1677773486388",
      "rating": {
        "oneStars": 0,
        "twoStars": 0,
        "threeStars": 3,
        "fourStars": 4,
        "fiveStars": 5,
        "averageStars": 4.3,
        "totalRatings": 12
      },
      "reviews": 47,
      "releaseDate": "2022-10-01",
      "popularity": 7
    },
    {
      "id": "P83K2",
      "name": "Aquamarine",
      "info": "Elegant clutch",
      "description": "Elegant aquamarine satin clutch",
      "details": "The aquamarine clutch is an elegant accessory that adds a touch of glamour to any ensemble. Crafted from luxurious satin, it features a compact design with a secure snap closure. The interior is lined with soft fabric and offers enough space for your essentials. Whether for a wedding, cocktail party, or a special occasion, this aquamarine clutch is the perfect companion to elevate your style.",
      "brand": "Prada",
      "size": "Small",
      "category": "handbags",
      "color": "aquamarine",
      "price": 49.99,
      "discount": 0.50,
      "qty": 12,
      "url": "https://static.zara.net/photos///2023/S/1/1/p/6001/110/254/2/w/581/6001110254_15_5_1.jpg?ts=1688478810962",
      "rating": {
        "oneStars": 0,
        "twoStars": 1,
        "threeStars": 2,
        "fourStars": 3,
        "fiveStars": 5,
        "averageStars": 3.9,
        "totalRatings": 11
      },
      "reviews": 28,
      "releaseDate": "2021-12-31",
      "popularity": 6
    },
    {
      "id": "Z79X6",
      "name": "Off White",
      "info": "Chic hobo bag",
      "description": "Chic off white leather hobo bag",
      "details": "The off white hobo bag combines style and functionality in a single accessory. Made from premium leather, it offers a roomy interior with a magnetic closure for easy access to your belongings. The adjustable shoulder strap provides comfort, and the additional zippered pocket keeps your essentials secure. With its versatile design and timeless appeal, this off white hobo bag is a fashionable choice for everyday use.",
      "brand": "Prada",
      "size": "Big",
      "category": "handbags",
      "color": "off white",
      "price": 159.99,
      "discount": 0.20,
      "qty": 9,
      "url": "https://static.zara.net/photos///2023/W/1/1/p/6174/110/612/2/w/535/6174110612_15_6_1.jpg?ts=1680096841333",
      "rating": {
        "oneStars": 1,
        "twoStars": 2,
        "threeStars": 4,
        "fourStars": 4,
        "fiveStars": 5,
        "averageStars": 4.2,
        "totalRatings": 16
      },
      "reviews": 61,
      "releaseDate": "2022-06-25",
      "popularity": 8
    },
    {
      "id": "D43K8",
      "name": "Muave",
      "info": "Vibrant satchel",
      "description": "Vibrant muave orange faux leather satchel",
      "details": "The muave orange satchel is a vibrant and eye-catching accessory. Crafted from high-quality faux leather, it offers durability and a luxurious look. The spacious main compartment and multiple pockets provide ample storage for your belongings. The detachable shoulder strap allows for versatile styling options. With its bold color and practical design, this muave orange satchel is sure to make a statement wherever you go.",
      "brand": "Biba",
      "size": "Medium",
      "category": "handbags",
      "color": "muave orange",
      "price": 199.99,
      "discount": 0.15,
      "qty": 5,
      "url": "https://static.zara.net/photos///2023/S/1/1/p/6004/110/713/2/w/614/6004110713_15_1_1.jpg?ts=1688382662085",
      "rating": {
        "oneStars": 0,
        "twoStars": 1,
        "threeStars": 2,
        "fourStars": 3,
        "fiveStars": 4,
        "averageStars": 3.8,
        "totalRatings": 10
      },
      "reviews": 23,
      "releaseDate": "2022-02-14",
      "popularity": 6
    },
    {
      "id": "Z65P9",
      "name": "Tote",
      "info": "Classic tote",
      "description": "Classic blue leather tote",
      "details": "The blue leather tote is a timeless accessory that combines style and practicality. Made from genuine leather, it offers a spacious interior with a zippered pocket and multiple compartments for organization. The sturdy handles and detachable shoulder strap provide versatility in carrying options. With its classic design and durable construction, this blue leather tote is a perfect companion for everyday activities and work.",
      "brand": "Biba",
      "size": "Big",
      "category": "handbags",
      "color": "Blue",
      "price": 289.99,
      "discount": 0.10,
      "qty": 10,
      "url": "https://static.zara.net/photos///2023/S/1/1/p/6895/011/700/2/w/372/6895011700_15_1_1.jpg?ts=1683884129345",
      "rating": {
        "oneStars": 0,
        "twoStars": 1,
        "threeStars": 3,
        "fourStars": 5,
        "fiveStars": 5,
        "averageStars": 4.4,
        "totalRatings": 14
      },
      "reviews": 48,
      "releaseDate": "2022-01-06",
      "popularity": 9
    },
    {
      "id": "1ab3cd",
      "name": "Chrono",
      "info": "Stylish timepiece",
      "description": "Stylish timepiece with blue dial",
      "details": "The Blue Chrono Watch is a stylish timepiece that combines elegance and functionality. Its blue dial adds a touch of sophistication to any outfit. With precise quartz movement and a durable stainless steel case, this watch is built to last. The adjustable strap ensures a comfortable fit for any wrist size. Whether for everyday wear or special occasions, the Blue Chrono Watch is the perfect accessory.",
      "brand": "Zara",
      "size": "Medium",
      "category": "watches",
      "color": "Blue",
      "price": 89.99,
      "discount": 0.4,
      "qty": 8,
      "url": "https://www.dolcegabbana.com/dw/image/v2/AAGA_PRD/on/demandware.static/-/Sites-15/default/dw2b7be663/images/zoom/WWEEGGWW045_8B267_0.jpg?sw=640&sh=816&sm=fit",
      "rating": {
        "oneStars": 2,
        "twoStars": 4,
        "threeStars": 6,
        "fourStars": 9,
        "fiveStars": 12,
        "averageStars": 3.9,
        "totalRatings": 33
      },
      "reviews": 35,
      "releaseDate": "2022-05-15",
      "popularity": 7
    },
    {
      "id": "2de4fg",
      "name": "Classic",
      "info": "Timeless design",
      "description": "Timeless design with maroon red strap",
      "details": "The Maroon Red Classic Watch features a timeless design that never goes out of style. Its maroon red strap adds a pop of color to your wrist, while the sleek stainless steel case exudes elegance. This watch is powered by a reliable automatic movement and is water-resistant up to 50 meters. With its versatile and sophisticated look, the Maroon Red Classic Watch is suitable for any occasion.",
      "brand": "Zara",
      "size": "Medium",
      "category": "watches",
      "color": "Maroon Red",
      "price": 149.99,
      "discount": 0.2,
      "qty": 10,
      "url": "https://www.dolcegabbana.com/dw/image/v2/AAGA_PRD/on/demandware.static/-/Sites-15/default/dw91b9b87c/images/zoom/WWFE1SWW066_N0000_0.jpg?sw=640&sh=816&sm=fit",
      "rating": {
        "oneStars": 1,
        "twoStars": 3,
        "threeStars": 5,
        "fourStars": 8,
        "fiveStars": 10,
        "averageStars": 3.8,
        "totalRatings": 27
      },
      "reviews": 27,
      "releaseDate": "2022-03-10",
      "popularity": 8
    },
    {
      "id": "3gh5ij",
      "name": "Sports",
      "info": "Designed lifestyles",
      "description": "Designed for active lifestyles with crimson red accents",
      "details": "The Crimson Red Sports Watch is specifically designed for those with active lifestyles. With its durable construction and water resistance up to 100 meters, this watch can withstand the demands of various sports and outdoor activities. The crimson red accents on the dial and strap add a bold touch of style. The chronograph function allows you to time your workouts with precision. Stay active and stylish with the Crimson Red Sports Watch.",
      "brand": "Dolce & Gabbana",
      "size": "Big",
      "category": "watches",
      "color": "Crimson Red",
      "price": 199.99,
      "discount": 0.3,
      "qty": 5,
      "url": "https://www.dolcegabbana.com/dw/image/v2/AAGA_PRD/on/demandware.static/-/Sites-15/default/dwf3145aae/images/zoom/WWFE1SWWB71_B0321_0.jpg?sw=640&sh=816&sm=fit",
      "rating": {
        "oneStars": 0,
        "twoStars": 2,
        "threeStars": 4,
        "fourStars": 7,
        "fiveStars": 9,
        "averageStars": 4.1,
        "totalRatings": 22
      },
      "reviews": 22,
      "releaseDate": "2022-07-28",
      "popularity": 6
    },
    {
      "id": "4kl6mn",
      "name": "Fashion",
      "info": "Trendy and chic",
      "description": "Trendy and chic watch in seinna pink",
      "details": "The Seinna Pink Fashion Watch is a trendy and chic accessory that adds a pop of color to any outfit. The seinna pink dial and strap create a playful and vibrant look. With its reliable quartz movement and stainless steel case, this watch combines style and durability. Whether you're going to a party or a casual outing, the Seinna Pink Fashion Watch is sure to turn heads.",
      "brand": "Dolce & Gabbana",
      "size": "Small",
      "category": "watches",
      "color": "Seinna Pink",
      "price": 79.99,
      "discount": 0.1,
      "qty": 12,
      "url": "https://www.dolcegabbana.com/dw/image/v2/AAGA_PRD/on/demandware.static/-/Sites-15/default/dwd159dbfb/images/zoom/WWFE1SWWB69_R0012_0.jpg?sw=640&sh=816&sm=fit",
      "rating": {
        "oneStars": 3,
        "twoStars": 5,
        "threeStars": 7,
        "fourStars": 10,
        "fiveStars": 13,
        "averageStars": 4.2,
        "totalRatings": 38
      },
      "reviews": 38,
      "releaseDate": "2022-02-05",
      "popularity": 9
    },
    {
      "id": "5op7qr",
      "name": "Casual",
      "info": "Casual and versatile",
      "description": "Casual and versatile watch in teal",
      "details": "The Teal Casual Watch is perfect for those seeking a casual and versatile timepiece. Its teal strap and minimalist design make it suitable for everyday wear. The stainless steel case provides durability, and the quartz movement ensures accurate timekeeping. Whether you're running errands or meeting friends, the Teal Casual Watch adds a touch of style to your wrist.",
      "brand": "Hennes & Mauritz",
      "size": "Medium",
      "category": "watches",
      "color": "Teal",
      "price": 59.99,
      "discount": 0.5,
      "qty": 3,
      "url": "https://www.dolcegabbana.com/dw/image/v2/AAGA_PRD/on/demandware.static/-/Sites-15/default/dwb49cca99/images/zoom/WWEE1MWWS08_B0321_0.jpg?sw=640&sh=816&sm=fit",
      "rating": {
        "oneStars": 1,
        "twoStars": 3,
        "threeStars": 5,
        "fourStars": 8,
        "fiveStars": 11,
        "averageStars": 3.9,
        "totalRatings": 26
      },
      "reviews": 28,
      "releaseDate": "2022-11-20",
      "popularity": 5
    },
    {
      "id": "6st9uv",
      "name": "Diving",
      "info": "For adventures",
      "description": "For underwater adventures with aquamarine accents",
      "details": "The Aquamarine Diving Watch is designed for underwater adventurers. With its high water resistance of up to 200 meters, this watch is suitable for diving and other water sports. The aquamarine accents on the dial and bezel add a touch of flair to its rugged design. Equipped with a reliable automatic movement, the Aquamarine Diving Watch is built to withstand the elements. Dive into your next adventure with confidence.",
      "brand": "Chanel",
      "size": "Big",
      "category": "watches",
      "color": "aquamarine",
      "price": 299.99,
      "discount": 0.2,
      "qty": 7,
      "url": "https://www.dolcegabbana.com/dw/image/v2/AAGA_PRD/on/demandware.static/-/Sites-15/default/dw2e8163fb/images/zoom/WWEE1MWWS09_R5232_0.jpg?sw=640&sh=816&sm=fit",
      "rating": {
        "oneStars": 0,
        "twoStars": 2,
        "threeStars": 4,
        "fourStars": 7,
        "fiveStars": 9,
        "averageStars": 4.1,
        "totalRatings": 28
      },
      "reviews": 24,
      "releaseDate": "2022-09-12",
      "popularity": 6
    },
    {
      "id": "7wx1yz",
      "name": "Luxury",
      "info": "Sophisticated",
      "description": "Elegant and sophisticated watch in off white",
      "details": "The Off White Luxury Watch exudes elegance and sophistication. Its off white strap and gold-tone accents create a luxurious look. The precise quartz movement ensures accurate timekeeping, while the stainless steel case provides durability. This watch is suitable for formal occasions or when you want to elevate your style. Make a statement with the Off White Luxury Watch.",
      "brand": "Prada",
      "size": "Medium",
      "category": "watches",
      "color": "off white",
      "price": 249.99,
      "discount": 0.3,
      "qty": 9,
      "url": "https://www.dolcegabbana.com/dw/image/v2/AAGA_PRD/on/demandware.static/-/Sites-15/default/dw93b41f05/images/zoom/WWEE1MWWS11_W0111_0.jpg?sw=640&sh=816&sm=fit",
      "rating": {
        "oneStars": 1,
        "twoStars": 4,
        "threeStars": 6,
        "fourStars": 9,
        "fiveStars": 11,
        "averageStars": 4.0,
        "totalRatings": 15
      },
      "reviews": 31,
      "releaseDate": "2022-06-02",
      "popularity": 7
    },
    {
      "id": "8ab2cd",
      "name": "Fashion",
      "info": "Vibrant",
      "description": "Vibrant and stylish watch in muave orange",
      "details": "The Muave Orange Fashion Watch is a vibrant and stylish accessory that adds a pop of color to your ensemble. Its muave orange dial and strap create an eye-catching look. The quartz movement ensures accurate timekeeping, while the stainless steel case provides durability. Whether you're going to a party or a casual outing, the Muave Orange Fashion Watch is sure to make a statement.",
      "brand": "Prada",
      "size": "Small",
      "category": "watches",
      "color": "muave orange",
      "price": 79.99,
      "discount": 0.1,
      "qty": 12,
      "url": "https://www.dolcegabbana.com/dw/image/v2/AAGA_PRD/on/demandware.static/-/Sites-15/default/dwf72f367b/images/zoom/WWEE1MWWS10_G7525_0.jpg?sw=640&sh=816&sm=fit",
      "rating": {
        "oneStars": 2,
        "twoStars": 5,
        "threeStars": 8,
        "fourStars": 11,
        "fiveStars": 14,
        "averageStars": 4.2,
        "totalRatings": 13
      },
      "reviews": 40,
      "releaseDate": "2022-01-18",
      "popularity": 9
    },
    {
      "id": "9de4fg",
      "name": "Chronograph",
      "info": "Sleek and functional",
      "description": "Sleek and functional watch with blue dial and chronograph",
      "details": "The Blue Dial Chronograph Watch combines sleek design with impressive functionality. The blue dial adds a touch of sophistication, while the chronograph feature allows you to measure elapsed time with precision. With its reliable quartz movement and stainless steel case, this watch is built to last. Whether for business meetings or casual outings, the Blue Dial Chronograph Watch is a versatile timepiece that complements any style.",
      "brand": "Biba",
      "size": "Medium",
      "category": "watches",
      "color": "Blue",
      "price": 179.99,
      "discount": 0.2,
      "qty": 10,
      "url": "https://www.dolcegabbana.com/dw/image/v2/AAGA_PRD/on/demandware.static/-/Sites-15/default/dwcd59ca35/images/zoom/WWEE1MWWS12_N3207_0.jpg?sw=640&sh=816&sm=fit",
      "rating": {
        "oneStars": 0,
        "twoStars": 3,
        "threeStars": 5,
        "fourStars": 8,
        "fiveStars": 10,
        "averageStars": 4.1,
        "totalRatings": 26
      },
      "reviews": 26,
      "releaseDate": "2022-04-05",
      "popularity": 8
    },
    {
      "id": "0gh5ij",
      "name": "Leather Strap",
      "info": "Classic",
      "description": "Classic and timeless watch with maroon red leather strap",
      "details": "The Maroon Red Leather Strap Watch offers a classic and timeless design that never goes out of style. The maroon red leather strap adds a touch of sophistication, while the stainless steel case provides durability. With its precise quartz movement and elegant dial, this watch is suitable for both formal and casual occasions. Elevate your look with the Maroon Red Leather Strap Watch.",
      "brand": "Biba",
      "size": "Small",
      "category": "watches",
      "color": "Maroon Red",
      "price": 129.99,
      "discount": 0.1,
      "qty": 8,
      "url": "https://www.dolcegabbana.com/dw/image/v2/AAGA_PRD/on/demandware.static/-/Sites-15/default/dw97808e20/images/zoom/WWEE1GWW020_87534_0.jpg?sw=640&sh=816&sm=fit",
      "rating": {
        "oneStars": 1,
        "twoStars": 4,
        "threeStars": 6,
        "fourStars": 8,
        "fiveStars": 10,
        "averageStars": 3.9,
        "totalRatings": 24
      },
      "reviews": 29,
      "releaseDate": "2022-02-20",
      "popularity": 7
    },
    {
      "id": "B01ACR9GJK",
      "name": "Cream",
      "info": "Moisturizing",
      "description": "Moisturizing and Nourishing Skincare Cream",
      "details": "This Blue Skincare Cream is specially formulated to deeply moisturize and nourish your skin. With its unique blend of natural ingredients, it helps to hydrate and rejuvenate your skin, leaving it soft, supple, and glowing. The lightweight formula absorbs quickly, making it suitable for all skin types. Pamper yourself with this luxurious cream and enjoy healthier-looking skin.",
      "brand": "Zara",
      "size": "Medium",
      "category": "skincare",
      "color": "Blue",
      "price": 29.99,
      "discount": 0.40,
      "qty": 8,
      "url": "https://www.dolcegabbana.com/dw/image/v2/AAGA_PRD/on/demandware.static/-/Sites-15/default/dwc5be6c40/images/zoom/MKUPFCE0015_V0000_0.jpg?sw=640&sh=816&sm=fit",
      "rating": {
        "oneStars": 2,
        "twoStars": 3,
        "threeStars": 5,
        "fourStars": 4,
        "fiveStars": 3,
        "averageStars": 3.3,
        "totalRatings": 36
      },
      "reviews": 63,
      "releaseDate": "2023-05-15",
      "popularity": 8
    },
    {
      "id": "D04YD1KG3",
      "name": "Face Serum",
      "info": "Revitalizing",
      "description": "Revitalizing and Anti-Aging Face Serum",
      "details": "Experience the rejuvenating power of our Maroon Red Face Serum. Infused with potent antioxidants and natural extracts, this serum helps to reduce the appearance of fine lines, wrinkles, and age spots, leaving your skin looking firmer and more youthful. The lightweight formula absorbs quickly and deeply nourishes your skin, giving it a healthy and radiant glow. Incorporate this serum into your skincare routine and let your natural beauty shine through.",
      "brand": "Zara",
      "size": "Small",
      "category": "skincare",
      "color": "Maroon Red",
      "price": 49.99,
      "discount": 0.20,
      "qty": 5,
      "url": "https://www.dolcegabbana.com/dw/image/v2/AAGA_PRD/on/demandware.static/-/Sites-15/default/dwf7f784f5/images/zoom/MKUPEYE0010_V0000_0.jpg?sw=640&sh=816&sm=fit",
      "rating": {
        "oneStars": 1,
        "twoStars": 2,
        "threeStars": 3,
        "fourStars": 4,
        "fiveStars": 4,
        "averageStars": 3.6,
        "totalRatings": 15
      },
      "reviews": 47,
      "releaseDate": "2023-04-21",
      "popularity": 6
    },
    {
      "id": "H29L8D7E4",
      "name": "Lip Balm",
      "info": "Nourishing",
      "description": "Moisturizing and Nourishing Lip Balm",
      "details": "Keep your lips hydrated and smooth with our Crimson Red Lip Balm. Enriched with natural oils and butters, this lip balm provides long-lasting moisture, while the vibrant crimson red color adds a touch of glamour to your look. Whether you're facing dry, cold winters or hot, sunny summers, this lip balm is your perfect companion for soft and supple lips all year round.",
      "brand": "Dolce & Gabbana",
      "size": "Big",
      "category": "skincare",
      "color": "Crimson Red",
      "price": 9.99,
      "discount": 0.10,
      "qty": 12,
      "url": "https://www.dolcegabbana.com/dw/image/v2/AAGA_PRD/on/demandware.static/-/Sites-15/default/dwf86c3afb/images/zoom/MKUPLIP0008_V0001_0.jpg?sw=640&sh=816&sm=fit",
      "rating": {
        "oneStars": 0,
        "twoStars": 1,
        "threeStars": 2,
        "fourStars": 3,
        "fiveStars": 4,
        "averageStars": 3.8,
        "totalRatings": 58
      },
      "reviews": 57,
      "releaseDate": "2023-01-05",
      "popularity": 9
    },
    {
      "id": "P76V9KA0C",
      "name": "Face Mask",
      "info": "Purifying",
      "description": "Purifying and Refreshing Face Mask",
      "details": "Indulge in the ultimate pampering session with our Seinna Pink Face Mask. This luxurious mask is infused with natural clays and botanical extracts, which work together to purify your skin, remove impurities, and minimize the appearance of pores. The refreshing formula revitalizes tired skin, leaving it soft, smooth, and glowing. Treat yourself to a spa-like experience at home and reveal a radiant complexion with this rejuvenating face mask.",
      "brand": "Dolce & Gabbana",
      "size": "Medium",
      "category": "skincare",
      "color": "Seinna Pink",
      "price": 19.99,
      "discount": 0.60,
      "qty": 2,
      "url": "https://www.dolcegabbana.com/dw/image/v2/AAGA_PRD/on/demandware.static/-/Sites-15/default/dw1f851139/images/zoom/MKUPFCE0012_V0004_0.jpg?sw=640&sh=816&sm=fit",
      "rating": {
        "oneStars": 3,
        "twoStars": 2,
        "threeStars": 4,
        "fourStars": 3,
        "fiveStars": 2,
        "averageStars": 2.9,
        "totalRatings": 24
      },
      "reviews": 54,
      "releaseDate": "2023-03-10",
      "popularity": 5
    },
    {
      "id": "B38FK3A9J",
      "name": "Body Lotion",
      "info": "Nourishing",
      "description": "Hydrating and Nourishing Body Lotion",
      "details": "Pamper your skin with our Teal Body Lotion. Enriched with moisturizing ingredients, this lotion provides long-lasting hydration and nourishment, leaving your skin feeling soft, smooth, and supple. The refreshing teal color and delightful scent make each application a luxurious experience. Treat your skin to the care it deserves with this indulgent body lotion.",
      "brand": "Hennes & Mauritz",
      "size": "Big",
      "category": "skincare",
      "color": "Teal",
      "price": 14.99,
      "discount": 0.30,
      "qty": 10,
      "url": "https://www.dolcegabbana.com/dw/image/v2/AAGA_PRD/on/demandware.static/-/Sites-15/default/dwf542732e/images/zoom/MKUPFCE0012_V0001_0.jpg?sw=640&sh=816&sm=fit",
      "rating": {
        "oneStars": 1,
        "twoStars": 3,
        "threeStars": 4,
        "fourStars": 3,
        "fiveStars": 2,
        "averageStars": 3.1,
        "totalRatings": 17
      },
      "reviews": 63,
      "releaseDate": "2023-02-12",
      "popularity": 7
    },
    {
      "id": "C61A8GZ9K",
      "name": "Face Scrub",
      "info": "Exfoliating",
      "description": "Exfoliating and Revitalizing Face Scrub",
      "details": "Achieve a fresh and radiant complexion with our Aquamarine Face Scrub. This invigorating scrub gently exfoliates and removes dead skin cells, revealing a smoother and more youthful-looking complexion. Enriched with nourishing ingredients, it revitalizes your skin and leaves it feeling refreshed and revitalized. Treat yourself to a spa-like experience and enjoy the transformative power of this rejuvenating face scrub.",
      "brand": "Hennes & Mauritz",
      "size": "Small",
      "category": "skincare",
      "color": "aquamarine",
      "price": 12.99,
      "discount": 0.50,
      "qty": 6,
      "url": "https://www.dolcegabbana.com/dw/image/v2/AAGA_PRD/on/demandware.static/-/Sites-15/default/dwf2789534/images/zoom/MKUPFCE0012_V0003_0.jpg?sw=640&sh=816&sm=fit",
      "rating": {
        "oneStars": 2,
        "twoStars": 2,
        "threeStars": 3,
        "fourStars": 4,
        "fiveStars": 3,
        "averageStars": 3.3,
        "totalRatings": 24
      },
      "reviews": 38,
      "releaseDate": "2023-03-27",
      "popularity": 4
    },
    {
      "id": "Z94Q2HL1B",
      "name": "Hand Cream",
      "info": "Softening",
      "description": "Moisturizing and Softening Hand Cream",
      "details": "Nourish and protect your hands with our Off White Hand Cream. Formulated with hydrating ingredients, this cream moisturizes and softens your skin, leaving it feeling silky smooth. The non-greasy formula absorbs quickly, providing instant relief for dry and chapped hands. Keep your hands looking and feeling their best with this luxurious hand cream.",
      "brand": "Chanel",
      "size": "Medium",
      "category": "skincare",
      "color": "off white",
      "price": 24.99,
      "discount": 0.15,
      "qty": 9,
      "url": "https://www.dolcegabbana.com/dw/image/v2/AAGA_PRD/on/demandware.static/-/Sites-15/default/dwd70e7032/images/zoom/MKUPEYE0006_V0007_0.jpg?sw=640&sh=816&sm=fit",
      "rating": {
        "oneStars": 0,
        "twoStars": 1,
        "threeStars": 2,
        "fourStars": 4,
        "fiveStars": 5,
        "averageStars": 4.2,
        "totalRatings": 11
      },
      "reviews": 89,
      "releaseDate": "2023-06-18",
      "popularity": 10
    },
    {
      "id": "D21V9LKC0",
      "name": "Facial Cleanser",
      "info": "Refreshing",
      "description": "Gentle and Refreshing Facial Cleanser",
      "details": "Start and end your day with our Muave Orange Facial Cleanser. This gentle yet effective cleanser removes dirt, oil, and impurities, leaving your skin feeling fresh, clean, and revitalized. Formulated with natural extracts and antioxidants, it helps to balance your skin's moisture levels and promote a healthy complexion. Treat yourself to the ultimate cleansing experience with this refreshing facial cleanser.",
      "brand": "Chanel",
      "size": "Small",
      "category": "skincare",
      "color": "muave orange",
      "price": 16.99,
      "discount": 0.25,
      "qty": 4,
      "url": "https://www.dolcegabbana.com/dw/image/v2/AAGA_PRD/on/demandware.static/-/Sites-15/default/dw34e20a09/images/zoom/MKUPFCE0000_V0002_0.jpg?sw=640&sh=816&sm=fit",
      "rating": {
        "oneStars": 1,
        "twoStars": 2,
        "threeStars": 3,
        "fourStars": 3,
        "fiveStars": 4,
        "averageStars": 3.4,
        "totalRatings": 29
      },
      "reviews": 45,
      "releaseDate": "2023-05-02",
      "popularity": 5
    },
    {
      "id": "P38FB9LZ6",
      "name": "Face Oil",
      "info": "Rejuvenating",
      "description": "Nourishing and Rejuvenating Face Oil",
      "details": "Restore your skin's natural radiance with our Blueberry Face Oil. This lightweight and fast-absorbing oil is packed with antioxidants and essential nutrients that nourish and rejuvenate your skin. It helps to reduce the appearance of fine lines, wrinkles, and age spots, while leaving your skin feeling soft, smooth, and hydrated. Incorporate this face oil into your skincare routine and enjoy a youthful and luminous complexion.",
      "brand": "Prada",
      "size": "Big",
      "category": "skincare",
      "color": "Blue",
      "price": 39.99,
      "discount": 0.30,
      "qty": 7,
      "url": "https://www.dolcegabbana.com/dw/image/v2/AAGA_PRD/on/demandware.static/-/Sites-15/default/dwe3d3f433/images/zoom/MKUPFCE0000_V0009_0.jpg?sw=640&sh=816&sm=fit",
      "rating": {
        "oneStars": 0,
        "twoStars": 2,
        "threeStars": 4,
        "fourStars": 5,
        "fiveStars": 4,
        "averageStars": 4.2,
        "totalRatings": 16
      },
      "reviews": 78,
      "releaseDate": "2023-04-06",
      "popularity": 9
    },
    {
      "id": "B92G7LK3F",
      "name": "Night Cream",
      "info": "Hydrating",
      "description": "Hydrating and Restorative Night Cream",
      "details": "Wake up to rejuvenated and nourished skin with our Maroon Red Night Cream. This luxurious cream is specifically designed to hydrate and restore your skin while you sleep. Infused with powerful antioxidants and hydrating ingredients, it helps to reduce the appearance of fine lines and wrinkles, leaving your skin looking plump, firm, and radiant. Transform your nighttime skincare routine with this indulgent night cream.",
      "brand": "Prada",
      "size": "Medium",
      "category": "skincare",
      "color": "Maroon Red",
      "price": 34.99,
      "discount": 0.20,
      "qty": 3,
      "url": "https://www.dolcegabbana.com/dw/image/v2/AAGA_PRD/on/demandware.static/-/Sites-15/default/dwe0f49fe9/images/zoom/MKUPFCE0000_V0011_0.jpg?sw=640&sh=816&sm=fit",
      "rating": {
        "oneStars": 1,
        "twoStars": 1,
        "threeStars": 3,
        "fourStars": 4,
        "fiveStars": 5,
        "averageStars": 4.0,
        "totalRatings": 12
      },
      "reviews": 60,
      "releaseDate": "2023-03-14",
      "popularity": 7
    },
    {
      "id": "H63V9AK0Z",
      "name": "Eye Serum",
      "info": "Brightening",
      "description": "Brightening and Anti-Aging Eye Serum",
      "details": "Revitalize your under-eye area with our Crimson Red Eye Serum. This potent serum is specially formulated to brighten and reduce the appearance of dark circles and puffiness. Enriched with powerful antioxidants and anti-aging ingredients, it helps to firm and smooth the delicate skin around your eyes, giving you a more youthful and radiant look. Add this luxurious eye serum to your skincare routine and say goodbye to tired-looking eyes.",
      "brand": "Biba",
      "size": "Small",
      "category": "skincare",
      "color": "Crimson Red",
      "price": 29.99,
      "discount": 0.40,
      "qty": 8,
      "url": "https://www.dolcegabbana.com/dw/image/v2/AAGA_PRD/on/demandware.static/-/Sites-15/default/dwdb5aa2b2/images/zoom/MKUPLIP0007_V0001_0.jpg?sw=640&sh=816&sm=fit",
      "rating": {
        "oneStars": 0,
        "twoStars": 0,
        "threeStars": 2,
        "fourStars": 4,
        "fiveStars": 5,
        "averageStars": 4.4,
        "totalRatings": 23
      },
      "reviews": 78,
      "releaseDate": "2023-02-21",
      "popularity": 8
    },
    {
      "id": "P1X0TY",
      "name": "Necklace",
      "info": "Elegant",
      "description": "Elegant gem necklace with blue stones",
      "details": "The Blue Gem Necklace is a stunning piece of jewelry that will add a touch of elegance to any outfit. The necklace features a beautiful arrangement of blue stones that catch the light and sparkle with every movement. It is the perfect accessory for a special occasion or a night out. The necklace is crafted with care and attention to detail, ensuring that it will last for years to come. The length of the necklace can be adjusted to suit your preference. It comes in a beautiful gift box, making it an excellent choice for a present. Add a touch of sophistication to your look with the Blue Gem Necklace.",
      "brand": "Zara",
      "size": "Medium",
      "category": "jewellery",
      "color": "Blue",
      "price": 59.99,
      "discount": 0.3,
      "qty": 8,
      "url": "https://www.prada.com/content/dam/pradabkg_products/1/1JO/1JO903/2CKSF0I89/1JO903_2CKS_F0I89_SLF.jpg/_jcr_content/renditions/cq5dam.web.hebebed.800.800.jpg",
      "rating": {
        "oneStars": 2,
        "twoStars": 3,
        "threeStars": 4,
        "fourStars": 3,
        "fiveStars": 5,
        "averageStars": 3.6,
        "totalRatings": 24
      },
      "reviews": 120,
      "releaseDate": "2023-03-15",
      "popularity": 7
    },
    {
      "id": "P2W9KF",
      "name": "Earrings",
      "info": "Stylish",
      "description": "Stylish maroon red earrings with a unique design",
      "details": "Make a bold statement with the Maroon Red Earrings. These earrings feature a stunning maroon red color that will complement any outfit. The unique design adds a touch of elegance and sophistication. The earrings are lightweight and comfortable to wear, making them perfect for all-day use. They are crafted with high-quality materials to ensure durability and longevity. The Maroon Red Earrings are suitable for both casual and formal occasions. They come in a beautiful gift box, making them an excellent choice for a present. Elevate your style with the Maroon Red Earrings.",
      "brand": "Zara",
      "size": "Small",
      "category": "jewellery",
      "color": "Maroon Red",
      "price": 39.99,
      "discount": 0.2,
      "qty": 5,
      "url": "https://www.prada.com/content/dam/pradanux_products/1/1JB/1JB303/2DTOF0118/1JB303_2DTO_F0118_SLF.png/_jcr_content/renditions/cq5dam.web.hebebed.800.800.jpg",
      "rating": {
        "oneStars": 1,
        "twoStars": 2,
        "threeStars": 4,
        "fourStars": 3,
        "fiveStars": 4,
        "averageStars": 3.4,
        "totalRatings": 14
      },
      "reviews": 88,
      "releaseDate": "2023-04-02",
      "popularity": 6
    },
    {
      "id": "P3R7GJ",
      "name": "Bracelet",
      "info": "Charming",
      "description": "Charming crimson red bracelet with a delicate design",
      "details": "Enhance your wrist with the Crimson Red Bracelet. This bracelet features a charming crimson red color that will catch everyone's attention. The delicate design adds a touch of femininity and elegance. It is adjustable to fit different wrist sizes and can be worn comfortably all day long. The Crimson Red Bracelet is made with high-quality materials to ensure durability and long-lasting beauty. Whether you're attending a special event or simply want to add a pop of color to your everyday look, this bracelet is the perfect choice. It comes in a stylish gift box, making it an ideal present for yourself or someone special. Embrace your inner style with the Crimson Red Bracelet.",
      "brand": "Dolce & Gabbana",
      "size": "Small",
      "category": "jewellery",
      "color": "Crimson Red",
      "price": 79.99,
      "discount": 0.1,
      "qty": 10,
      "url": "https://static.zara.net/photos///2023/V/0/1/p/4736/192/303/2/w/295/4736192303_6_21_1.jpg?ts=1681198715892",
      "rating": {
        "oneStars": 0,
        "twoStars": 1,
        "threeStars": 2,
        "fourStars": 3,
        "fiveStars": 5,
        "averageStars": 3.9,
        "totalRatings": 23
      },
      "reviews": 145,
      "releaseDate": "2023-01-22",
      "popularity": 8
    },
    {
      "id": "P4U6ND",
      "name": "Ring",
      "info": "Elegant pink ring",
      "description": "Elegant seinna pink ring with a timeless design",
      "details": "Make a statement with the Seinna Pink Ring. This ring features an elegant seinna pink color that exudes sophistication. The timeless design makes it a versatile piece that can be worn on any occasion. The ring is crafted with precision and attention to detail, ensuring a comfortable fit and long-lasting beauty. It is made with high-quality materials that are resistant to tarnishing and fading. The Seinna Pink Ring is available in different sizes to suit your preference. It comes in a stylish gift box, making it a perfect choice for a present. Elevate your style with the Seinna Pink Ring.",
      "brand": "Dolce & Gabbana",
      "size": "Big",
      "category": "jewellery",
      "color": "Seinna Pink",
      "price": 129.99,
      "discount": 0.4,
      "qty": 3,
      "url": "https://static.zara.net/photos///2023/V/0/1/p/1856/129/303/2/w/614/1856129303_6_21_1.jpg?ts=1681385725278",
      "rating": {
        "oneStars": 1,
        "twoStars": 1,
        "threeStars": 3,
        "fourStars": 4,
        "fiveStars": 5,
        "averageStars": 4.1,
        "totalRatings": 22
      },
      "reviews": 212,
      "releaseDate": "2023-05-10",
      "popularity": 9
    },
    {
      "id": "P5S2ZA",
      "name": "Teal Necklace",
      "info": "Stunning necklace",
      "description": "Stunning teal necklace with a modern design",
      "details": "Add a pop of color to your outfit with the Teal Necklace. This necklace features a stunning teal color that will catch everyone's attention. The modern design adds a touch of sophistication and elegance. The necklace is adjustable to suit your desired length and can be worn comfortably all day long. It is made with high-quality materials that are resistant to tarnishing and fading. The Teal Necklace is perfect for both casual and formal occasions. It comes in a beautiful gift box, making it an excellent choice for a present. Make a bold fashion statement with the Teal Necklace.",
      "brand": "Hennes & Mauritz",
      "size": "Medium",
      "category": "jewellery",
      "color": "Teal",
      "price": 69.99,
      "discount": 0.6,
      "qty": 7,
      "url": "https://static.zara.net/photos///2023/V/0/1/p/1856/093/303/2/w/298/1856093303_6_21_1.jpg?ts=1679912526964",
      "rating": {
        "oneStars": 2,
        "twoStars": 3,
        "threeStars": 4,
        "fourStars": 3,
        "fiveStars": 4,
        "averageStars": 3.6,
        "totalRatings": 12
      },
      "reviews": 177,
      "releaseDate": "2023-06-05",
      "popularity": 8
    },
    {
      "id": "P6B1PC",
      "name": "Earrings",
      "info": "Elegant earrings",
      "description": "Elegant aquamarine earrings with a classic design",
      "details": "Enhance your look with the Aquamarine Earrings. These earrings feature an elegant aquamarine color that exudes beauty and grace. The classic design makes them suitable for both casual and formal occasions. The earrings are lightweight and comfortable to wear, making them perfect for all-day use. They are made with high-quality materials that are resistant to tarnishing and fading. The Aquamarine Earrings come in a stylish gift box, making them an excellent choice for a present. Elevate your style with the Aquamarine Earrings and add a touch of sophistication to any outfit.",
      "brand": "Hennes & Mauritz",
      "size": "Small",
      "category": "jewellery",
      "color": "aquamarine",
      "price": 49.99,
      "discount": 0.3,
      "qty": 9,
      "url": "https://www.dolcegabbana.com/dw/image/v2/AAGA_PRD/on/demandware.static/-/Sites-15/default/dw902b648b/images/zoom/WNFA4GWAM01_ZOO00_0.jpg?sw=640&sh=816&sm=fit",
      "rating": {
        "oneStars": 0,
        "twoStars": 1,
        "threeStars": 3,
        "fourStars": 4,
        "fiveStars": 5,
        "averageStars": 4.1,
        "totalRatings": 18
      },
      "reviews": 218,
      "releaseDate": "2023-02-18",
      "popularity": 7
    },
    {
      "id": "P7M8EF",
      "name": "Off Bracelet",
      "info": "Charming bracelet",
      "description": "Charming off white bracelet with a delicate design",
      "details": "Complete your look with the Off White Bracelet. This bracelet features a charming off white color that will complement any outfit. The delicate design adds a touch of femininity and elegance. It is adjustable to fit different wrist sizes and can be worn comfortably all day long. The Off White Bracelet is made with high-quality materials to ensure durability and long-lasting beauty. Whether you're attending a special event or simply want to add a subtle touch to your everyday look, this bracelet is the perfect choice. It comes in a stylish gift box, making it an ideal present for yourself or someone special. Embrace your inner style with the Off White Bracelet.",
      "brand": "Chanel",
      "size": "Medium",
      "category": "jewellery",
      "color": "off white",
      "price": 79.99,
      "discount": 0.1,
      "qty": 4,
      "url": "https://www.dolcegabbana.com/dw/image/v2/AAGA_PRD/on/demandware.static/-/Sites-15/default/dwa6607f32/images/zoom/WNFA2GWQC01_ZOO00_0.jpg?sw=640&sh=816&sm=fit",
      "rating": {
        "oneStars": 1,
        "twoStars": 2,
        "threeStars": 4,
        "fourStars": 3,
        "fiveStars": 4,
        "averageStars": 3.4,
        "totalRatings": 23
      },
      "reviews": 123,
      "releaseDate": "2023-03-05",
      "popularity": 6
    },
    {
      "id": "P8R3VY",
      "name": "Orange Ring",
      "info": "Stylish ring",
      "description": "Stylish muave orange ring with a unique design",
      "details": "Make a statement with the Muave Orange Ring. This ring features a stylish muave orange color that will catch everyone's attention. The unique design adds a touch of elegance and sophistication. The ring is crafted with precision and attention to detail, ensuring a comfortable fit and long-lasting beauty. It is made with high-quality materials that are resistant to tarnishing and fading. The Muave Orange Ring is available in different sizes to suit your preference. It comes in a beautiful gift box, making it a perfect choice for a present. Elevate your style with the Muave Orange Ring.",
      "brand": "Chanel",
      "size": "Big",
      "category": "jewellery",
      "color": "muave orange",
      "price": 119.99,
      "discount": 0.2,
      "qty": 2,
      "url": "https://www.dolcegabbana.com/dw/image/v2/AAGA_PRD/on/demandware.static/-/Sites-15/default/dw373f59df/images/zoom/WELB1GWMIX1_ZOO00_A.jpg?sw=640&sh=816&sm=fit",
      "rating": {
        "oneStars": 0,
        "twoStars": 1,
        "threeStars": 2,
        "fourStars": 3,
        "fiveStars": 5,
        "averageStars": 3.9,
        "totalRatings": 28
      },
      "reviews": 99,
      "releaseDate": "2023-04-18",
      "popularity": 7
    },
    {
      "id": "P9G7KQ",
      "name": "Gem Bracelet",
      "info": "Elegant bracelet",
      "description": "Elegant blue gem bracelet with a timeless design",
      "details": "Enhance your wrist with the Blue Gem Bracelet. This bracelet features an elegant blue gem color that exudes sophistication. The timeless design makes it a versatile piece that can be worn on any occasion. The bracelet is adjustable to fit different wrist sizes and can be worn comfortably all day long. It is made with high-quality materials that are resistant to tarnishing and fading. The Blue Gem Bracelet comes in a stylish gift box, making it an excellent choice for a present. Elevate your style with the Blue Gem Bracelet and add a touch of elegance to any outfit.",
      "brand": "Prada",
      "size": "Medium",
      "category": "jewellery",
      "color": "Blue",
      "price": 89.99,
      "discount": 0.4,
      "qty": 6,
      "url": "https://www.dolcegabbana.com/dw/image/v2/AAGA_PRD/on/demandware.static/-/Sites-15/default/dw4d18a34d/images/zoom/WRJI1GWAM01_ZOO00_0.jpg?sw=640&sh=816&sm=fit",
      "rating": {
        "oneStars": 1,
        "twoStars": 1,
        "threeStars": 3,
        "fourStars": 4,
        "fiveStars": 5,
        "averageStars": 4.1,
        "totalRatings": 26
      },
      "reviews": 187,
      "releaseDate": "2023-05-02",
      "popularity": 9
    },
    {
      "id": "P0N2WX",
      "name": "Maroon Earrings",
      "info": "Stunning earrings",
      "description": "Stunning maroon red earrings with a modern design",
      "details": "Add a pop of color to your look with the Maroon Red Earrings. These earrings feature a stunning maroon red color that will catch everyone's attention. The modern design adds a touch of sophistication and elegance. The earrings are lightweight and comfortable to wear, making them perfect for all-day use. They are made with high-quality materials that are resistant to tarnishing and fading. The Maroon Red Earrings come in a stylish gift box, making them an excellent choice for a present. Elevate your style with the Maroon Red Earrings and make a fashion statement.",
      "brand": "Prada",
      "size": "Small",
      "category": "jewellery",
      "color": "Maroon Red",
      "price": 59.99,
      "discount": 0.3,
      "qty": 11,
      "url": "https://www.dolcegabbana.com/dw/image/v2/AAGA_PRD/on/demandware.static/-/Sites-15/default/dw1016899b/images/zoom/WANR2GWMIXE_ZOO00_0.jpg?sw=640&sh=816&sm=fit",
      "rating": {
        "oneStars": 0,
        "twoStars": 2,
        "threeStars": 4,
        "fourStars": 3,
        "fiveStars": 4,
        "averageStars": 3.6,
        "totalRatings": 23
      },
      "reviews": 216,
      "releaseDate": "2023-01-15",
      "popularity": 8
    },
    {
      "id": "P1Q4LB",
      "name": "Seinna Necklace",
      "info": "Elegant necklace",
      "description": "Elegant seinna pink necklace with a classic design",
      "details": "Enhance your look with the Seinna Pink Necklace. This necklace features an elegant seinna pink color that exudes beauty and grace. The classic design makes it suitable for both casual and formal occasions. The necklace is adjustable to suit your desired length and can be worn comfortably all day long. It is made with high-quality materials that are resistant to tarnishing and fading. The Seinna Pink Necklace comes in a stylish gift box, making it an excellent choice for a present. Elevate your style with the Seinna Pink Necklace and add a touch of sophistication to any outfit.",
      "brand": "Biba",
      "size": "Big",
      "category": "jewellery",
      "color": "Seinna Pink",
      "price": 119.99,
      "discount": 0.2,
      "qty": 3,
      "url": "https://www.dolcegabbana.com/dw/image/v2/AAGA_PRD/on/demandware.static/-/Sites-15/default/dwf28966da/images/zoom/WBFA4GWAM01_ZOO00_0.jpg?sw=640&sh=816&sm=fit",
      "rating": {
        "oneStars": 1,
        "twoStars": 1,
        "threeStars": 3,
        "fourStars": 4,
        "fiveStars": 5,
        "averageStars": 4.1,
        "totalRatings": 29
      },
      "reviews": 211,
      "releaseDate": "2023-03-28",
      "popularity": 7
    },
    {
      "id": "P2T7JO",
      "name": "Teal Bracelet",
      "info": "Charming bracelet",
      "description": "Charming teal bracelet with a delicate design",
      "details": "Complete your look with the Teal Bracelet. This bracelet features a charming teal color that will complement any outfit. The delicate design adds a touch of femininity and elegance. It is adjustable to fit different wrist sizes and can be worn comfortably all day long. The Teal Bracelet is made with high-quality materials to ensure durability and long-lasting beauty. Whether you're attending a special event or simply want to add a subtle touch to your everyday look, this bracelet is the perfect choice. It comes in a stylish gift box, making it an ideal present for yourself or someone special. Embrace your inner style with the Teal Bracelet.",
      "brand": "Biba",
      "size": "Medium",
      "category": "jewellery",
      "color": "Teal",
      "price": 79.99,
      "discount": 0.1,
      "qty": 5,
      "url": "https://www.dolcegabbana.com/dw/image/v2/AAGA_PRD/on/demandware.static/-/Sites-15/default/dw7a13dc42/images/zoom/WBMI4GWAMC1_ZOO00_0.jpg?sw=640&sh=816&sm=fit",
      "rating": {
        "oneStars": 2,
        "twoStars": 3,
        "threeStars": 4,
        "fourStars": 3,
        "fiveStars": 4,
        "averageStars": 3.6,
        "totalRatings": 15
      },
      "reviews": 177,
      "releaseDate": "2023-06-01",
      "popularity": 6
    },
    {
      "id": "P3X2DK",
      "name": "Ring",
      "info": "Stylish ring",
      "description": "Stylish aquamarine ring with a unique design",
      "details": "Make a statement with the Aquamarine Ring. This ring features a stylish aquamarine color that will catch everyone's attention. The unique design adds a touch of elegance and sophistication. The ring is crafted with precision and attention to detail, ensuring a comfortable fit and long-lasting beauty. It is made with high-quality materials that are resistant to tarnishing and fading. The Aquamarine Ring is available in different sizes to suit your preference. It comes in a beautiful gift box, making it a perfect choice for a present. Elevate your style with the Aquamarine Ring.",
      "brand": "Zara",
      "size": "Small",
      "category": "jewellery",
      "color": "aquamarine",
      "price": 49.99,
      "discount": 0.3,
      "qty": 9,
      "url": "https://www.dolcegabbana.com/dw/image/v2/AAGA_PRD/on/demandware.static/-/Sites-15/default/dw328a1ad0/images/zoom/WEQR3GWMIX1_ZOO00_0.jpg?sw=640&sh=816&sm=fit",
      "rating": {
        "oneStars": 0,
        "twoStars": 1,
        "threeStars": 3,
        "fourStars": 4,
        "fiveStars": 5,
        "averageStars": 4.1,
        "totalRatings": 18
      },
      "reviews": 218,
      "releaseDate": "2023-02-14",
      "popularity": 7
    },
    {
      "id": "P4E9IH",
      "name": "Off White",
      "info": "Elegant necklace",
      "description": "Elegant off white necklace with a timeless design",
      "details": "Enhance your neck with the Off White Necklace. This necklace features an elegant off white color that exudes sophistication. The timeless design makes it a versatile piece that can be worn on any occasion. The necklace is adjustable to suit your desired length and can be worn comfortably all day long. It is made with high-quality materials that are resistant to tarnishing and fading. The Off White Necklace comes in a stylish gift box, making it an excellent choice for a present. Elevate your style with the Off White Necklace and add a touch of elegance to any outfit.",
      "brand": "Dolce & Gabbana",
      "size": "Medium",
      "category": "jewellery",
      "color": "off white",
      "price": 99.99,
      "discount": 0.4,
      "qty": 4,
      "url": "https://static.zara.net/photos///2023/S/0/1/p/1124/250/303/3/w/469/1124250303_15_11_1.jpg?ts=1688546691274",
      "rating": {
        "oneStars": 1,
        "twoStars": 2,
        "threeStars": 4,
        "fourStars": 3,
        "fiveStars": 4,
        "averageStars": 3.8,
        "totalRatings": 29
      },
      "reviews": 204,
      "releaseDate": "2023-04-07",
      "popularity": 8
    },
    {
      "id": "P5R8ZM",
      "name": "Muave Orange",
      "info": "Stylish earrings",
      "description": "Stylish muave orange earrings with a modern design",
      "details": "Add a pop of color to your look with the Muave Orange Earrings. These earrings feature a stylish muave orange color that will catch everyone's attention. The modern design adds a touch of sophistication and elegance. The earrings are lightweight and comfortable to wear, making them perfect for all-day use. They are made with high-quality materials that are resistant to tarnishing and fading. The Muave Orange Earrings come in a stylish gift box, making them an excellent choice for a present. Elevate your style with the Muave Orange Earrings and make a fashion statement.",
      "brand": "Chanel",
      "size": "Big",
      "category": "jewellery",
      "color": "muave orange",
      "price": 79.99,
      "discount": 0.2,
      "qty": 7,
      "url": "https://static.zara.net/photos///2023/S/0/1/p/1124/249/303/3/w/469/1124249303_15_11_1.jpg?ts=1688546705488",
      "rating": {
        "oneStars": 0,
        "twoStars": 1,
        "threeStars": 3,
        "fourStars": 4,
        "fiveStars": 5,
        "averageStars": 4.1,
        "totalRatings": 29
      },
      "reviews": 195,
      "releaseDate": "2023-05-22",
      "popularity": 9
    },
    {
      "id": "P6T5XN",
      "name": "Gem Bracelet",
      "info": "Elegant bracelet",
      "description": "Elegant blue gem bracelet with a timeless design",
      "details": "Enhance your wrist with the Blue Gem Bracelet. This bracelet features an elegant blue gem color that exudes sophistication. The timeless design makes it a versatile piece that can be worn on any occasion. The bracelet is adjustable to fit different wrist sizes and can be worn comfortably all day long. It is made with high-quality materials that are resistant to tarnishing and fading. The Blue Gem Bracelet comes in a stylish gift box, making it an excellent choice for a present. Elevate your style with the Blue Gem Bracelet and add a touch of elegance to any outfit.",
      "brand": "Dolce & Gabbana",
      "size": "Medium",
      "category": "jewellery",
      "color": "Blue",
      "price": 89.99,
      "discount": 0.4,
      "qty": 6,
      "url": "https://static.zara.net/photos///2023/V/0/1/p/4548/213/808/2/w/614/4548213808_6_21_1.jpg?ts=1681974800357",
      "rating": {
        "oneStars": 1,
        "twoStars": 1,
        "threeStars": 3,
        "fourStars": 4,
        "fiveStars": 5,
        "averageStars": 4.1,
        "totalRatings": 21
      },
      "reviews": 199,
      "releaseDate": "2023-03-10",
      "popularity": 8
    },
    {
      "id": "AB12CD",
      "name": "Blue Shirt",
      "info": "Comfortable",
      "description": "Comfortable cotton shirt in blue",
      "details": "This blue shirt is made of high-quality cotton fabric, providing exceptional comfort and breathability. It features a classic design with a button-down collar and a chest pocket. The shirt is perfect for both casual and formal occasions, offering a versatile addition to your wardrobe. With its vibrant blue color, it adds a stylish touch to any outfit. Available in small, medium, and big sizes.",
      "brand": "Zara",
      "size": "Medium",
      "category": "apparels",
      "color": "Blue",
      "price": 39.99,
      "discount": 0.6,
      "qty": 8,
      "url": "https://www.prada.com/content/dam/pradabkg_products/U/UCS/UCS438/1VIVF067K/UCS438_1VIV_F067K_S_231_SLF.jpg/_jcr_content/renditions/cq5dam.web.hebebed.800.800.jpg",
      "rating": {
        "oneStars": 1,
        "twoStars": 3,
        "threeStars": 5,
        "fourStars": 7,
        "fiveStars": 9,
        "averageStars": 2.8,
        "totalRatings": 21
      },
      "reviews": 63,
      "releaseDate": "2023-06-15",
      "popularity": 7
    },
    {
      "id": "EF34GH",
      "name": "Maroon Dress",
      "info": "Elegant evening",
      "description": "Elegant evening dress in maroon",
      "details": "Make a stunning impression at any special occasion with this elegant maroon dress. Crafted from premium quality fabric, this dress offers a comfortable and flattering fit. It features a V-neckline, a fitted waist, and a flowy skirt that adds a touch of sophistication to your look. The rich maroon color enhances the dress's beauty, making it a perfect choice for formal events. Available in small, medium, and big sizes.",
      "brand": "Zara",
      "size": "Small",
      "category": "apparels",
      "color": "Maroon Red",
      "price": 89.99,
      "discount": 0.3,
      "qty": 5,
      "url": "https://www.prada.com/content/dam/pradabkg_products/U/UPW/UPW468/13CRF098L/UPW468_13CR_F098L_S_231_SLF.jpg/_jcr_content/renditions/cq5dam.web.hebebed.800.800.jpg",
      "rating": {
        "oneStars": 2,
        "twoStars": 4,
        "threeStars": 6,
        "fourStars": 8,
        "fiveStars": 10,
        "averageStars": 4.2,
        "totalRatings": 12
      },
      "reviews": 58,
      "releaseDate": "2023-05-21",
      "popularity": 8
    },
    {
      "id": "IJ56KL",
      "name": "Crimson",
      "info": "Stylish t-shirt",
      "description": "Soft and stylish t-shirt in crimson red",
      "details": "This crimson red t-shirt is a perfect blend of comfort and style. Made from soft and breathable fabric, it ensures all-day comfort. The t-shirt features a crew neck and short sleeves, making it a versatile option for casual outings. The vibrant crimson red color adds a pop of color to your outfit. Available in small, medium, and big sizes.",
      "brand": "Dolce & Gabbana",
      "size": "Big",
      "category": "apparels",
      "color": "Crimson Red",
      "price": 29.99,
      "discount": 0.2,
      "qty": 10,
      "url": "https://www.prada.com/content/dam/pradabkg_products/U/UMB/UMB588/1U1PF0480/UMB588_1U1P_F0480_S_231_SLF.jpg/_jcr_content/renditions/cq5dam.web.hebebed.800.800.jpg",
      "rating": {
        "oneStars": 0,
        "twoStars": 3,
        "threeStars": 4,
        "fourStars": 6,
        "fiveStars": 9,
        "averageStars": 4.1,
        "totalRatings": 29
      },
      "reviews": 22,
      "releaseDate": "2023-06-01",
      "popularity": 6
    },
    {
      "id": "MN78OP",
      "name": "Pink Blouse",
      "info": "Floral pattern",
      "description": "Stylish blouse with floral pattern in seinna pink",
      "details": "Add a touch of elegance to your wardrobe with this seinna pink blouse. It features a beautiful floral pattern and a relaxed fit, providing a chic and feminine look. The blouse is made from high-quality fabric, ensuring durability and comfort. The seinna pink color adds a charming appeal to the overall design. Perfect for both casual and formal occasions. Available in small, medium, and big sizes.",
      "brand": "Dolce & Gabbana",
      "size": "Small",
      "category": "apparels",
      "color": "Seinna Pink",
      "price": 49.99,
      "discount": 0.1,
      "qty": 12,
      "url": "https://www.prada.com/content/dam/pradabkg_products/S/SC6/SC609/12U9F03EM/SC609_12U9_F03EM_S_221_SLF.jpg/_jcr_content/renditions/cq5dam.web.hebebed.800.800.jpg",
      "rating": {
        "oneStars": 1,
        "twoStars": 2,
        "threeStars": 3,
        "fourStars": 7,
        "fiveStars": 9,
        "averageStars": 3.7,
        "totalRatings": 24
      },
      "reviews": 22,
      "releaseDate": "2023-05-10",
      "popularity": 5
    },
    {
      "id": "QR90ST",
      "name": "Teal Sweater",
      "info": "Warm sweater",
      "description": "Warm and cozy sweater in teal",
      "details": "Stay warm and stylish with this teal sweater. Crafted from a blend of high-quality materials, it offers exceptional warmth and comfort. The sweater features a crew neck, long sleeves, and ribbed cuffs and hem for a snug fit. The beautiful teal color adds a vibrant touch to your winter wardrobe. Perfect for layering or wearing on its own. Available in small, medium, and big sizes.",
      "brand": "Hennes & Mauritz",
      "size": "Big",
      "category": "apparels",
      "color": "Teal",
      "price": 59.99,
      "discount": 0.4,
      "qty": 3,
      "url": "https://www.prada.com/content/dam/pradabkg_products/G/GEC/GEC073/12CDF0F4Q/GEC073_12CD_F0F4Q_S_222_SLF.jpg/_jcr_content/renditions/cq5dam.web.hebebed.800.800.jpg",
      "rating": {
        "oneStars": 0,
        "twoStars": 1,
        "threeStars": 4,
        "fourStars": 6,
        "fiveStars": 9,
        "averageStars": 4.0,
        "totalRatings": 16
      },
      "reviews": 18,
      "releaseDate": "2023-04-17",
      "popularity": 4
    },
    {
      "id": "UV12WX",
      "name": "Jeans",
      "info": "Stylish jeans",
      "description": "Stylish and comfortable jeans in aquamarine",
      "details": "These aquamarine jeans combine style and comfort effortlessly. Made from premium denim fabric, they offer a flattering fit and excellent durability. The jeans feature a classic five-pocket design and a straight-leg silhouette, making them versatile for various outfits. The aquamarine color adds a refreshing and vibrant touch to your casual look. Available in small, medium, and big sizes.",
      "brand": "Hennes & Mauritz",
      "size": "Medium",
      "category": "apparels",
      "color": "aquamarine",
      "price": 79.99,
      "discount": 0.5,
      "qty": 9,
      "url": "https://static.zara.net/photos///2023/S/0/1/p/3802/284/044/2/w/298/3802284044_6_1_1.jpg?ts=1688639900112",
      "rating": {
        "oneStars": 1,
        "twoStars": 2,
        "threeStars": 3,
        "fourStars": 5,
        "fiveStars": 8,
        "averageStars": 3.8,
        "totalRatings": 19
      },
      "reviews": 33,
      "releaseDate": "2023-05-05",
      "popularity": 6
    },
    {
      "id": "YZ34AB",
      "name": "Blazer",
      "info": "Classic blazer",
      "description": "Classic off white blazer with a modern twist",
      "details": "Step up your style game with this classic off white blazer. Made from high-quality fabric, it offers a comfortable fit and excellent craftsmanship. The blazer features a modern twist with unique lapel details and a tailored silhouette. Whether you're heading to a business meeting or a social event, this blazer will make you stand out. Available in small, medium, and big sizes.",
      "brand": "Chanel",
      "size": "Small",
      "category": "apparels",
      "color": "off white",
      "price": 199.99,
      "discount": 0.9,
      "qty": 4,
      "url": "https://www.dolcegabbana.com/dw/image/v2/AAGA_PRD/on/demandware.static/-/Sites-15/default/dw8d620409/images/zoom/F6AHJTFI5G0_HH4KV_0.jpg?sw=640&sh=816&sm=fit",
      "rating": {
        "oneStars": 0,
        "twoStars": 0,
        "threeStars": 2,
        "fourStars": 5,
        "fiveStars": 7,
        "averageStars": 4.2,
        "totalRatings": 22
      },
      "reviews": 14,
      "releaseDate": "2023-05-30",
      "popularity": 3
    },
    {
      "id": "CD56EF",
      "name": "Muave Skirt",
      "info": "Stylish skirt",
      "description": "Stylish A-line skirt in muave orange",
      "details": "Make a bold statement with this muave orange A-line skirt. Crafted from premium fabric, it offers a comfortable and flattering fit. The skirt features a high waist and a flowy silhouette, exuding elegance and femininity. The vibrant muave orange color adds a pop of color to your outfit, perfect for both casual and formal occasions. Available in small, medium, and big sizes.",
      "brand": "Prada",
      "size": "Big",
      "category": "apparels",
      "color": "muave orange",
      "price": 79.99,
      "discount": 0.7,
      "qty": 7,
      "url": "https://www.dolcegabbana.com/dw/image/v2/AAGA_PRD/on/demandware.static/-/Sites-15/default/dw96e52e9b/images/zoom/F5P61TFI5G4_HH4KO_0.jpg?sw=640&sh=816&sm=fit",
      "rating": {
        "oneStars": 1,
        "twoStars": 3,
        "threeStars": 4,
        "fourStars": 6,
        "fiveStars": 8,
        "averageStars": 3.9,
        "totalRatings": 23
      },
      "reviews": 27,
      "releaseDate": "2023-06-10",
      "popularity": 7
    },
    {
      "id": "GH78IJ",
      "name": "Blue Shirt",
      "info": "Classic shirt",
      "description": "Classic polo shirt in blue",
      "details": "Upgrade your casual wardrobe with this classic blue polo shirt. Crafted from high-quality cotton fabric, it offers exceptional comfort and breathability. The shirt features a traditional polo collar, short sleeves, and a button placket. The versatile blue color makes it a perfect choice for various occasions, from a casual day out to a smart-casual gathering. Available in small, medium, and big sizes.",
      "brand": "Biba",
      "size": "Medium",
      "category": "apparels",
      "color": "Blue",
      "price": 49.99,
      "discount": 0.2,
      "qty": 11,
      "url": "https://www.dolcegabbana.com/dw/image/v2/AAGA_PRD/on/demandware.static/-/Sites-15/default/dwb3208280/images/zoom/F8S21TGDBUE_S9000_0.jpg?sw=640&sh=816&sm=fit",
      "rating": {
        "oneStars": 0,
        "twoStars": 2,
        "threeStars": 4,
        "fourStars": 7,
        "fiveStars": 9,
        "averageStars": 4.1,
        "totalRatings": 27
      },
      "reviews": 37,
      "releaseDate": "2023-05-15",
      "popularity": 8
    },
    {
      "id": "KL90MN",
      "name": "Maroon Red",
      "info": "Chic",
      "description": "Chic blouse with lace details in maroon red",
      "details": "Make a fashion statement with this chic maroon red blouse. It features intricate lace details and a relaxed fit, combining elegance and comfort. The blouse is made from high-quality fabric, ensuring durability and a luxurious feel. The maroon red color adds a touch of sophistication to any outfit, making it suitable for both formal and casual occasions. Available in small, medium, and big sizes.",
      "brand": "Biba",
      "size": "Small",
      "category": "apparels",
      "color": "Maroon Red",
      "price": 69.99,
      "discount": 0.3,
      "qty": 6,
      "url": "https://www.dolcegabbana.com/dw/image/v2/AAGA_PRD/on/demandware.static/-/Sites-15/default/dw77c6df05/images/zoom/F4CHDTHI1MJ_HH4KT_0.jpg?sw=640&sh=816&sm=fit",
      "rating": {
        "oneStars": 1,
        "twoStars": 2,
        "threeStars": 4,
        "fourStars": 6,
        "fiveStars": 9,
        "averageStars": 3.9,
        "totalRatings": 19
      },
      "reviews": 25,
      "releaseDate": "2023-04-28",
      "popularity": 9
    }
  ],
  "categories": [
    "handbags",
    "watches",
    "skincare",
    "jewellery",
    "apparels"
  ],
  "colors": [
    "Blue",
    "Maroon Red",
    "Crimson Red",
    "Seinna Pink",
    "Teal",
    "Aquamarine",
    "Off-White",
    "Muave Orange"
  ],
  "brands": [
    "Zara",
    "Dolce & Gabbana",
    "Hennes & Mauritz",
    "Chanel",
    "Prada",
    "Biba"
  ]
}

  